web_youtube_dl/__init__.py
web_youtube_dl/app/api.py
web_youtube_dl/app/main.py
web_youtube_dl/app/static/favicon.ico
web_youtube_dl/app/templates/index.html
web_youtube_dl/app/utils.py
web_youtube_dl/app/views.py
web_youtube_dl/config.py
web_youtube_dl/services/__init__.py
web_youtube_dl/services/metadata.py
web_youtube_dl/services/progress.py
web_youtube_dl/services/websockets.py
web_youtube_dl/services/youtube.py
web_youtube_dl-0.3.0.dist-info/entry_points.txt
web_youtube_dl-0.3.0.dist-info/LICENSE
web_youtube_dl-0.3.0.dist-info/WHEEL
web_youtube_dl-0.3.0.dist-info/METADATA
web_youtube_dl-0.3.0.dist-info/RECORD
