Metadata-Version: 2.1
Name: web-youtube-dl
Version: 0.3.0
Summary: A web version of youtube-dl
Author: Uriel Mandujano
Author-email: uriel.mandujano14@gmail.com
Requires-Python: >=3.7,<4.0
Classifier: Programming Language :: Python :: 3
Classifier: Programming Language :: Python :: 3.10
Classifier: Programming Language :: Python :: 3.7
Classifier: Programming Language :: Python :: 3.8
Classifier: Programming Language :: Python :: 3.9
Classifier: Topic :: Home Automation
Classifier: Topic :: Multimedia :: Sound/Audio
Classifier: Topic :: Multimedia :: Sound/Audio :: Capture/Recording
Requires-Dist: Jinja2 (>=3.1.2,<4.0.0)
Requires-Dist: Werkzeug (>=1.0.1,<2.0.0)
Requires-Dist: aiofiles (>=0.5.0,<0.6.0)
Requires-Dist: fastapi (>=0,<1)
Requires-Dist: ffmpeg-python (>=0.2.0,<0.3.0)
Requires-Dist: janus (>=0.5.0,<0.6.0)
Requires-Dist: musicbrainzngs (>=0.7.1,<0.8.0)
Requires-Dist: mutagen (>=1.45.1,<2.0.0)
Requires-Dist: python-multipart (>=0.0.5,<0.0.6)
Requires-Dist: pytube (>=12.0.0,<13.0.0)
Requires-Dist: uvicorn (>=0.17.0,<0.18.0)
Requires-Dist: websockets (>=10.3,<11.0)
